QuPRS/__init__.py
QuPRS/_version.py
QuPRS/config.py
QuPRS/cache_manager/__init__.py
QuPRS/cache_manager/cache_decorator.py
QuPRS/cache_manager/global_cache_manager.py
QuPRS/interface/__init__.py
QuPRS/interface/gate_library.py
QuPRS/interface/load_qiskit.py
QuPRS/interface/ps2wmc.py
QuPRS/interface/qasm2qc.py
QuPRS/pathsum/__init__.py
QuPRS/pathsum/core.py
QuPRS/pathsum/core.pyi
QuPRS/pathsum/pattern_match.py
QuPRS/pathsum/reduction.py
QuPRS/pathsum/statistics.py
QuPRS/pathsum/gates/__init__.py
QuPRS/pathsum/gates/base.py
QuPRS/pathsum/gates/builder.py
QuPRS/pathsum/gates/multi_qubit.py
QuPRS/pathsum/gates/patcher.py
QuPRS/pathsum/gates/single_qubit.py
QuPRS/pathsum/gates/two_qubit.py
QuPRS/utils/Qiskit_Circuit_Utils.py
QuPRS/utils/__init__.py
QuPRS/utils/strategy.py
QuPRS/utils/util.py
QuPRS/utils/wmc_tools/ganak
QuPRS/utils/wmc_tools/gpmc
quprs.libs/libgmp-d944b113.so.10.3.2
quprs.libs/libgmpxx-8b3a383a.so.4.5.2
quprs.libs/libmpfr-b7fafdf8.so.4.1.6
quprs-0.12.2.dist-info/METADATA
quprs-0.12.2.dist-info/WHEEL
quprs-0.12.2.dist-info/RECORD
quprs-0.12.2.dist-info/licenses/LICENSE.md
quprs-0.12.2.dist-info/licenses/NOTICE.md
quprs-0.12.2.dist-info/sboms/auditwheel.cdx.json
