Metadata-Version: 2.4
Name: QuPRS
Version: 0.12.2
Summary: QuPRS: Quantum Path-sum Reduction and Solver
Project-URL: Homepage, https://github.com/PhysicsQoo/QuPRS
Project-URL: PyPI, https://pypi.org/project/QuPRS/
Project-URL: Bug Tracker, https://github.com/PhysicsQoo/QuPRS/issues
Project-URL: Documentation, https://github.com/PhysicsQoo/QuPRS#readme
Author-email: Wei-Jia Huang <wei.jia.huang.physics@gmail.com>
License-File: LICENSE.md
License-File: NOTICE.md
Keywords: equivalence checking,pathsum,quantum circuit,weighted model counting
Classifier: Development Status :: 4 - Beta
Classifier: Intended Audience :: Developers
Classifier: Intended Audience :: Science/Research
Classifier: License :: OSI Approved :: MIT License
Classifier: Operating System :: MacOS :: MacOS X
Classifier: Operating System :: POSIX :: Linux
Classifier: Programming Language :: Python :: 3
Classifier: Programming Language :: Python :: 3.11
Classifier: Programming Language :: Python :: 3.12
Classifier: Programming Language :: Python :: 3.13
Classifier: Topic :: Scientific/Engineering :: Electronic Design Automation (EDA)
Classifier: Topic :: Scientific/Engineering :: Mathematics
Classifier: Topic :: Scientific/Engineering :: Physics
Classifier: Topic :: Software Development :: Libraries :: Python Modules
Classifier: Topic :: Software Development :: Testing
Requires-Python: >=3.11
Requires-Dist: numpy
Requires-Dist: psutil
Requires-Dist: qiskit-qasm3-import>=0.5.1
Requires-Dist: qiskit<2.0,>=1.0.0
Requires-Dist: symengine
Requires-Dist: sympy
Provides-Extra: dev
Requires-Dist: build; extra == 'dev'
Requires-Dist: ipykernel; extra == 'dev'
Requires-Dist: pandas; extra == 'dev'
Requires-Dist: pytest; extra == 'dev'
Requires-Dist: pytest-benchmark; extra == 'dev'
Requires-Dist: pytest-codspeed; extra == 'dev'
Requires-Dist: pytest-cov; extra == 'dev'
Requires-Dist: pytest-flake8; extra == 'dev'
Requires-Dist: pytest-html; extra == 'dev'
Requires-Dist: pytest-xdist; extra == 'dev'
Requires-Dist: tqdm; extra == 'dev'
